datahosting/__init__.py
datahosting/client.py
datahosting/exceptions.py
datahosting_ipfs-1.0.0.dist-info/licenses/LICENSE
datahosting_ipfs-1.0.0.dist-info/METADATA
datahosting_ipfs-1.0.0.dist-info/WHEEL
datahosting_ipfs-1.0.0.dist-info/top_level.txt
datahosting_ipfs-1.0.0.dist-info/RECORD
