Metadata-Version: 2.4
Name: datahosting-ipfs
Version: 1.0.0
Summary: Python SDK for DataHosting IPFS hosting
Home-page: https://github.com/branislav1989/ipfs-kubo-private-public-ipfs-cluster
Author: Branislav Usjak
Author-email: branislavusjak1989@gmail.com
Classifier: Programming Language :: Python :: 3
Classifier: License :: OSI Approved :: MIT License
Requires-Python: >=3.8
License-File: LICENSE
Requires-Dist: requests>=2.28.0
Dynamic: author
Dynamic: author-email
Dynamic: classifier
Dynamic: description
Dynamic: description-content-type
Dynamic: home-page
Dynamic: license-file
Dynamic: requires-dist
Dynamic: requires-python
Dynamic: summary
